urlshort_python2/__init__.py
urlshort_python2/helpers.py
urlshort_python2/models.py
urlshort_python2/urls.py
urlshort_python2/utils.py
urlshort_python2/views.py
urlshort_python2/migrations/0001_initial.py
urlshort_python2/migrations/__init__.py
ldc_urlshort_python2-0.0.1.dist-info/METADATA
ldc_urlshort_python2-0.0.1.dist-info/WHEEL
ldc_urlshort_python2-0.0.1.dist-info/top_level.txt
ldc_urlshort_python2-0.0.1.dist-info/RECORD
