Metadata-Version: 2.1
Name: ldc-urlshort-python2
Version: 0.0.1
Summary: A simple package to shorten URLs
Home-page: UNKNOWN
Author: Pratik Kumar
Author-email: pratik.kumar@lendenclub.com
License: UNKNOWN
Platform: UNKNOWN
Classifier: Intended Audience :: Developers
Classifier: Programming Language :: Python :: 2.7
Classifier: Topic :: Utilities
Requires-Dist: django (==1.9.7)
Requires-Dist: djangorestframework (==3.5.4)
Requires-Dist: python-dateutil (==2.5.3)
